ctq/__init__.py
ctq/acquisition.py
ctq/acquisition_test.py
ctq/events.py
ctq/events_test.py
ctq/named_resource.py
ctq/named_resource_test.py
ctq/resource_cache.py
ctq/resource_cache_test.py
ctq/tests.py
ctq/traversal.py
ctq/traversal_test.py
ctq/workflow.py
ctq/workflow_test.py
ctq-0.1.dist-info/METADATA
ctq-0.1.dist-info/WHEEL
ctq-0.1.dist-info/top_level.txt
ctq-0.1.dist-info/RECORD
