Metadata-Version: 2.1
Name: ctq
Version: 0.1
Summary: UNKNOWN
Home-page: https://github.com/olivelink/ctq
Author: Olive Link Pty Ltd
Author-email: software@olivelink.net
License: UNKNOWN
Keywords: traversal context resource
Platform: UNKNOWN
Classifier: Programming Language :: Python
Classifier: Framework :: Pyramid
Requires-Dist: setuptools
Requires-Dist: cachetools
